mcp_server_videogenerator/__init__.py
mcp_server_videogenerator/__main__.py
mcp_server_videogenerator/videogenerator_server.py
mcp_server_videogenerator-0.0.4.dist-info/METADATA
mcp_server_videogenerator-0.0.4.dist-info/WHEEL
mcp_server_videogenerator-0.0.4.dist-info/entry_points.txt
mcp_server_videogenerator-0.0.4.dist-info/RECORD
